{"quote":"(Vict. Ant. e Cat. in Marc.) The blind man calls the Lord, the Son of David, hearing the way in which the passing multitude praised Him, and feeling sure that the expectation of the prophets was fulfilled. There follows: And many charged him that he should hold his peace.t","sources":[{"url":"https:\/\/www.ecatholic2000.com\/catena\/untitled-111.shtml","title":"Catena Aurea by Aquinas [ECATH]"},{"url":"https:\/\/ccel.org\/ccel\/aquinas\/catena2\/catena2.i.html","title":"Catena Aurea by Aquinas [CCEL]"}]}