{
    "quote": "In this clothing and this poor food, he shews that he sorrows for the sins of the whole human race.\n\nIn John (which name is interpreted 'the grace of God,') is figured Christ who brought grace into the world; in his clothing, the Gentile Church.",
    "sources": [
        {
            "url": "https:\/\/www.ecatholic2000.com\/catena\/untitled-111.shtml",
            "title": "Catena Aurea by Aquinas"
        },
        {
            "url": "https:\/\/ccel.org\/ccel\/aquinas\/catena1\/catena1.i.html",
            "title": "Catena Aurea by Aquinas"
        }
    ],
    "secondary_source": "Aquinas"
}